mcp_ui_explorer/__init__.py
mcp_ui_explorer/__main__.py
mcp_ui_explorer/hierarchical_ui_explorer.py
mcp_ui_explorer/config/__init__.py
mcp_ui_explorer/config/settings.py
mcp_ui_explorer/core/__init__.py
mcp_ui_explorer/core/actions.py
mcp_ui_explorer/core/tracking.py
mcp_ui_explorer/core/ui_explorer.py
mcp_ui_explorer/models/__init__.py
mcp_ui_explorer/models/enums.py
mcp_ui_explorer/models/inputs.py
mcp_ui_explorer/server/__init__.py
mcp_ui_explorer/server/mcp_server.py
mcp_ui_explorer/services/__init__.py
mcp_ui_explorer/services/macro_player.py
mcp_ui_explorer/services/macro_recorder.py
mcp_ui_explorer/services/memory.py
mcp_ui_explorer/services/ui_tars.py
mcp_ui_explorer/services/verification.py
mcp_ui_explorer/utils/__init__.py
mcp_ui_explorer/utils/coordinates.py
mcp_ui_explorer/utils/logging.py
mcp_ui_explorer/utils/system.py
mcp_ui_explorer-0.1.20.dist-info/licenses/LICENSE
mcp_ui_explorer-0.1.20.dist-info/METADATA
mcp_ui_explorer-0.1.20.dist-info/WHEEL
mcp_ui_explorer-0.1.20.dist-info/entry_points.txt
mcp_ui_explorer-0.1.20.dist-info/top_level.txt
mcp_ui_explorer-0.1.20.dist-info/RECORD
