Metadata-Version: 2.4
Name: mcp-ui-explorer
Version: 0.1.20
Summary: An MCP server for exploring and interacting with UI elements
Home-page: https://github.com/modularflow/mcp-ui-explorer
Author: UI Explorer Developer
Author-email: UI Explorer Developer <example@example.com>
License: MIT
Project-URL: Homepage, https://github.com/modularflow/mcp-ui-explorer
Project-URL: Issues, https://github.com/modularflow/mcp-ui-explorer/issues
Classifier: Programming Language :: Python :: 3
Classifier: Programming Language :: Python :: 3.10
Classifier: License :: OSI Approved :: MIT License
Classifier: Operating System :: Microsoft :: Windows
Requires-Python: >=3.10
License-File: LICENSE
Requires-Dist: pyautogui
Requires-Dist: pywinauto
Requires-Dist: pillow
Requires-Dist: pydantic>=2.0.0
Requires-Dist: mcp>=1.6.0
Requires-Dist: openai>=1.82.0
Requires-Dist: pynput
Provides-Extra: dev
Requires-Dist: pytest>=7.0.0; extra == "dev"
Requires-Dist: pytest-asyncio>=0.21.0; extra == "dev"
Requires-Dist: pytest-cov>=4.0.0; extra == "dev"
Requires-Dist: pytest-mock>=3.10.0; extra == "dev"
Requires-Dist: pytest-benchmark>=4.0.0; extra == "dev"
Requires-Dist: pytest-timeout>=2.1.0; extra == "dev"
Requires-Dist: black>=23.0.0; extra == "dev"
Requires-Dist: isort>=5.12.0; extra == "dev"
Requires-Dist: flake8>=6.0.0; extra == "dev"
Requires-Dist: mypy>=1.0.0; extra == "dev"
Requires-Dist: pylint>=2.17.0; extra == "dev"
Requires-Dist: bandit>=1.7.0; extra == "dev"
Requires-Dist: safety>=2.3.0; extra == "dev"
Requires-Dist: psutil>=5.9.0; extra == "dev"
Provides-Extra: test
Requires-Dist: pytest>=7.0.0; extra == "test"
Requires-Dist: pytest-asyncio>=0.21.0; extra == "test"
Requires-Dist: pytest-cov>=4.0.0; extra == "test"
Requires-Dist: pytest-mock>=3.10.0; extra == "test"
Requires-Dist: pytest-benchmark>=4.0.0; extra == "test"
Requires-Dist: pytest-timeout>=2.1.0; extra == "test"
Requires-Dist: psutil>=5.9.0; extra == "test"
Provides-Extra: lint
Requires-Dist: black>=23.0.0; extra == "lint"
Requires-Dist: isort>=5.12.0; extra == "lint"
Requires-Dist: flake8>=6.0.0; extra == "lint"
Requires-Dist: mypy>=1.0.0; extra == "lint"
Requires-Dist: pylint>=2.17.0; extra == "lint"
Requires-Dist: bandit>=1.7.0; extra == "lint"
Requires-Dist: safety>=2.3.0; extra == "lint"
Dynamic: author
Dynamic: home-page
Dynamic: license-file
Dynamic: requires-python
